pyglow/__init__.py
pyglow/mapping.py
pyglow/parser.py
pyglow/pyglow.py
pyglow/styles/__init__.py
pyglow/styles/background.py
pyglow/styles/border.py
pyglow/styles/foreground.py
pyglow/styles/style.py
pyglow/utilities/__init__.py
pyglow/utilities/color_utils.py
pyglow/utilities/utils.py
pyglow/views/__init__.py
pyglow/views/panel.py
pyglow/views/progressbar.py
pyglow/views/spinner.py
pyglow/views/table.py
pyglow/views/termpicker.py
pyglowx-1.6.0.dist-info/licenses/LICENSE
pyglowx-1.6.0.dist-info/METADATA
pyglowx-1.6.0.dist-info/WHEEL
pyglowx-1.6.0.dist-info/top_level.txt
pyglowx-1.6.0.dist-info/RECORD
