Metadata-Version: 2.4
Name: pyglowx
Version: 1.6.0
Summary: pyglow is a lightweight, feature rich, cross-platform, markdown-style console output formatter library for python.
Author-email: BirukBelihu <birukbelihu1995@email.com>
License: Apache-2.0
Project-URL: Homepage, https://github.com/birukbelihu/pyglow
Project-URL: Source, https://github.com/birukbelihu/pyglow
Project-URL: Issues, https://github.com/birukbelihu/pyglow/issues
Classifier: Programming Language :: Python :: 3.9
Classifier: Programming Language :: Python :: 3.10
Classifier: Programming Language :: Python :: 3.11
Classifier: Programming Language :: Python :: 3.12
Classifier: Programming Language :: Python :: 3.13
Requires-Python: >=3.9
License-File: LICENSE
Dynamic: license-file
